asreviewcontrib/wordcloud/__init__.py
asreviewcontrib/wordcloud/_version.py
asreviewcontrib/wordcloud/entrypoint.py
asreview_wordcloud-1.0.1.dist-info/LICENSE
asreview_wordcloud-1.0.1.dist-info/METADATA
asreview_wordcloud-1.0.1.dist-info/WHEEL
asreview_wordcloud-1.0.1.dist-info/entry_points.txt
asreview_wordcloud-1.0.1.dist-info/top_level.txt
asreview_wordcloud-1.0.1.dist-info/RECORD
