Metadata-Version: 2.1
Name: asreview-wordcloud
Version: 1.0.1
Summary: Wordcloud tools for the ASReview project
Home-page: https://github.com/asreview/asreview-wordcloud
Author: Utrecht University
Author-email: asreview@uu.nl
License: UNKNOWN
Project-URL: Bug Reports, https://github.com/asreview/asreview-wordcloud/issues
Project-URL: Source, https://github.com/asreview/asreview-wordcloud
Keywords: asreview wordcloud
Platform: UNKNOWN
Classifier: Development Status :: 5 - Production/Stable
Classifier: License :: OSI Approved :: MIT License
Classifier: Programming Language :: Python :: 3.7
Classifier: Programming Language :: Python :: 3.8
Classifier: Programming Language :: Python :: 3.9
Requires-Python: >=3.7
License-File: LICENSE
Requires-Dist: wordcloud
Requires-Dist: asreview (<2,>=1)
Requires-Dist: matplotlib
